pyxsim-4.4.3.dist-info/RECORD
pyxsim-4.4.3.dist-info/WHEEL
pyxsim-4.4.3.dist-info/top_level.txt
pyxsim-4.4.3.dist-info/METADATA
pyxsim-4.4.3.dist-info/licenses/COPYING.txt
pyxsim/event_list.py
pyxsim/xray_binaries.py
pyxsim/__init__.py
pyxsim/utils.py
pyxsim/spectral_models.py
pyxsim/photon_list.py
pyxsim/light_cone.py
pyxsim/tests/test_light_cone.py
pyxsim/tests/test_utils.py
pyxsim/tests/test_power_law.py
pyxsim/tests/conftest.py
pyxsim/tests/test_sloshing.py
pyxsim/tests/__init__.py
pyxsim/tests/test_line_emission.py
pyxsim/tests/test_beta_model.py
pyxsim/tests/test_pixel_to_cel.py
pyxsim/tests/utils.py
pyxsim/tests/coveragerc
pyxsim/tests/test_spectra.py
pyxsim/source_models/line_sources.py
pyxsim/source_models/thermal_sources.py
pyxsim/source_models/__init__.py
pyxsim/source_models/power_law_sources.py
pyxsim/source_models/sources.py
pyxsim/lib/spectra.cpython-312-darwin.so
pyxsim/lib/spectra.pyx
pyxsim/lib/sky_functions.pyx
pyxsim/lib/__init__.py
pyxsim/lib/interpolate.cpython-312-darwin.so
pyxsim/lib/interpolate.pyx
pyxsim/lib/sky_functions.cpython-312-darwin.so
