Metadata-Version: 2.4
Name: pyxsim
Version: 4.4.3
Summary: Python package for simulating X-ray observations from astrophysical sources
Home-page: http://github.com/jzuhone/pyxsim
Author-email: John ZuHone <jzuhone@gmail.com>
Classifier: Intended Audience :: Science/Research
Classifier: Operating System :: OS Independent
Classifier: Programming Language :: Python :: 3
Classifier: Topic :: Scientific/Engineering :: Visualization
Requires-Python: >=3.11
License-File: COPYING.txt
Requires-Dist: numpy
Requires-Dist: astropy>=4.0
Requires-Dist: h5py>=3.0
Requires-Dist: scipy
Requires-Dist: yt>=4.3
Requires-Dist: unyt>=2.9.5
Requires-Dist: soxs>=5.0.1
Requires-Dist: tqdm
Dynamic: home-page
Dynamic: license-file
